[{"s": "mozaika-u-ogurtsov-v-teplitse-chto-delat-foto", "t": "Мозаика у огурцов в теплице: что делать, фото симптомов и лечение", "i": "🥒", "c": "bolezni-ogurtsov"}, {"s": "mokh-v-teplitse-chto-delat-zelenyj", "t": "Мох в теплице: что делать, если появился зеленый налет и как убрать", "i": "🍆", "c": "ukhod-za-pertsami-i-baklazhanami"}, {"s": "monokalij-fosfat-kak-primenyat-dlya-ogurtsov-i-pomidorov-v-teplitse", "t": "Монокалий фосфат для огурцов и томатов: применение в теплице", "i": "🌿", "c": "posadka-i-udobreniya"}, {"s": "mochevina-dlya-pomidor-v-teplitse-kogda-primenyat", "t": "Мочевина для томатов в теплице: сроки, нормы и схемы внесения", "i": "🌿", "c": "posadka-i-udobreniya"}, {"s": "mozaika-na-pomidorakh-v-teplitse-kak-borotsya-foto", "t": "Мозаика на томатах в теплице: симптомы, лечение и профилактика", "i": "🍅", "c": "bolezni-tomatov"}, {"s": "mochevina-kak-razvodit-dlya-poliva-ogurtsov-v-teplitse", "t": "Мочевина для огурцов в теплице: как разводить и поливать правильно", "i": "🌿", "c": "posadka-i-udobreniya"}, {"s": "mozaika-na-listyakh-tomatov-v-teplitse-kak-lechit", "t": "Мозаика на листьях томатов: лечение, профилактика и борьба с вирусом", "i": "🍅", "c": "bolezni-tomatov"}, {"s": "molochnaya-syvorotka-dlya-rastenij-kak-udobrenie-v-teplitse-dlya-ogurtsov-i-pomidorov", "t": "Молочная сыворотка для огурцов и томатов: рецепт и польза в теплице", "i": "🌿", "c": "posadka-i-udobreniya"}, {"s": "mokritsy-v-zemle-v-teplitse-chto-delat", "t": "Мокрицы в земле в теплице: что делать и как быстро от них избавиться", "i": "🐛", "c": "vrediteli-i-zashchita"}, {"s": "mozhno-li-opilki-ispolzovat-kak-mulchu-v-teplitse", "t": "Опилки как мульча в теплице: польза, вред и правила применения", "i": "🟫", "c": "pochva-i-gryadki"}, {"s": "mokritsy-v-teplitse-kak-ot-nikh-izbavitsya", "t": "Мокрицы в теплице: как избавиться от вредителей навсегда", "i": "🐛", "c": "vrediteli-i-zashchita"}, {"s": "mokh-v-teplitse-chto-eto-znachit", "t": "Мох в теплице: причины появления и способы борьбы", "i": "🟫", "c": "pochva-i-gryadki"}, {"s": "molochnaya-syvorotka-dlya-rastenij-kak-udobrenie-v-teplitse", "t": "Молочная сыворотка для растений: удобрение в теплице", "i": "🌿", "c": "posadka-i-udobreniya"}, {"s": "mochevina-dlya-ogurtsov-v-teplitse-skolko-nuzhno-podkarmlivat", "t": "Мочевина для огурцов в теплице: нормы и сроки подкормки", "i": "🌿", "c": "posadka-i-udobreniya"}, {"s": "mozhno-li-obrezat-bolshie-listya-u-ogurtsov-v-teplitse-i-kak", "t": "Обрезка листьев огурцов в теплице: как и когда проводить", "i": "✂️", "c": "formirovanie-kustov"}, {"s": "mol-na-pomidorakh-v-teplitse-kak-izbavitsya", "t": "Моль на помидорах в теплице: эффективные методы борьбы и защиты", "i": "🐛", "c": "vrediteli-i-zashchita"}, {"s": "mokritsy-v-teplitse-kak-borotsya", "t": "Мокрицы в теплице: как бороться эффективно и безопасно", "i": "🐛", "c": "vrediteli-i-zashchita"}, {"s": "monokalij-fosfat-dlya-ogurtsov-v-teplitse-kak-primenyat", "t": "Монокалий фосфат для огурцов в теплице: как применять", "i": "🌿", "c": "posadka-i-udobreniya"}, {"s": "mokritsy-v-teplitse-kak-izbavitsya-seli-ves-perets", "t": "Мокрицы в теплице: как избавиться и спасти перец от уничтожения", "i": "🐛", "c": "vrediteli-i-zashchita"}, {"s": "mozhno-li-sushit-chesnok-v-teplitse-gde-rastut-pomidory", "t": "Сушка чеснока в теплице с томатами: риски, правила и совместимость", "i": "📅", "c": "sezonnye-raboty"}, {"s": "mozhno-li-srezat-nizhnie-listya-u-ogurtsov-v-teplitse-i-kak", "t": "Обрезка нижних листьев у огурцов в теплице: правила и сроки", "i": "✂️", "c": "formirovanie-kustov"}, {"s": "mokritsy-v-teplitse-kak-izbavitsya-seli-ogurtsy", "t": "Мокрицы в теплице: как избавиться и спасти огурцы раз и навсегда", "i": "🐛", "c": "vrediteli-i-zashchita"}, {"s": "monokalij-fosfat-dlya-ogurtsov-v-teplitse-kak", "t": "Монокалий фосфат для огурцов в теплице: как применять и дозировка", "i": "🌿", "c": "posadka-i-udobreniya"}, {"s": "mochevina-dlya-pertsev-v-teplitse-kogda-primenyat", "t": "Мочевина для перцев в теплице: сроки, нормы и способы внесения", "i": "🌿", "c": "posadka-i-udobreniya"}, {"s": "mokh-v-teplitse-chem-obrabotat", "t": "Мох в теплице: эффективная обработка и народные средства", "i": "🧪", "c": "obrabotka-i-dezinfektsiya"}, {"s": "montazh-polikarbonata-na-teplitsu-pri-kakoj-temperature", "t": "Монтаж поликарбоната на теплицу: температура и правила", "i": "🔨", "c": "postrojka-i-konstruktsiya"}, {"s": "mozhno-li-opryskivat-pomidory-fitosporinom-vo-vremya-plodonosheniya-v-teplitse-i-kak-opryskivat", "t": "Фитоспорин для томатов в теплице: обработка во время плодоношения", "i": "🧪", "c": "obrabotka-i-dezinfektsiya"}, {"s": "moshki-v-teplitse-chto-delat", "t": "Как избавиться от мошек в теплице: эффективные методы борьбы", "i": "🐛", "c": "vrediteli-i-zashchita"}, {"s": "mozaika-na-ogurtsakh-v-teplitse-kak-borotsya", "t": "Мозаика на огурцах в теплице: как бороться и предотвратить вирус", "i": "🥒", "c": "bolezni-ogurtsov"}, {"s": "mokh-na-zemle-v-teplitse-kak-izbavitsya", "t": "Как избавиться от мха в теплице: методы борьбы и профилактика", "i": "🟫", "c": "pochva-i-gryadki"}, {"s": "mokritsy-v-teplitse-kak", "t": "Мокрицы в теплице: причины появления и эффективная борьба", "i": "🐛", "c": "vrediteli-i-zashchita"}, {"s": "mokritsa-v-teplitse-kak-borotsya", "t": "Мокрица в теплице: как бороться и чем обработать почву", "i": "🐛", "c": "vrediteli-i-zashchita"}, {"s": "mozaika-na-ogurtsakh-v-teplitse-kak-borotsya-narodnye-sredstva", "t": "Мозаика на огурцах в теплице: как бороться народными средствами", "i": "🥒", "c": "bolezni-ogurtsov"}, {"s": "mozhno-li-seyat-gorchitsu-pod-zimu-kak-siderat-v-teplitse", "t": "Можно ли сеять горчицу под зиму в теплице: правила", "i": "🟫", "c": "pochva-i-gryadki"}, {"s": "moshka-na-luke-kak-izbavitsya-v-teplitse", "t": "Мошка на луке в теплице: как избавиться быстро и навсегда", "i": "🐛", "c": "vrediteli-i-zashchita"}, {"s": "mokrushki-v-teplitse-kak-izbavitsya", "t": "Мокрушки в теплице: как избавиться навсегда и защитить урожай", "i": "🐛", "c": "vrediteli-i-zashchita"}, {"s": "moshki-na-pomidorakh-v-teplitse-chem-obrabotat", "t": "Как избавиться от мошек на помидорах в теплице: эффективные методы", "i": "🐛", "c": "vrediteli-i-zashchita"}, {"s": "mokh-kak-mulcha-dlya-tomatov-v-teplitse", "t": "Мох как мульча для томатов: плюсы, минусы и технология использования", "i": "🟫", "c": "pochva-i-gryadki"}, {"s": "monolitnyj-polikarbonat-na-kryshu-teplitsy-kakaya-tolshchina", "t": "Толщина монолитного поликарбоната для крыши теплицы: выбор", "i": "🔨", "c": "postrojka-i-konstruktsiya"}, {"s": "monofosfat-kaliya-kak-podkormit-tomaty-v-teplitse", "t": "Монофосфат калия для томатов: подкормка в теплице, дозы и сроки", "i": "🌿", "c": "posadka-i-udobreniya"}, {"s": "mozhno-li-sazhat-salat-pod-zimu-i-kogda-v-teplitsu", "t": "Можно ли сажать салат под зиму и когда в теплицу: сроки и сорта", "i": "❄️", "c": "zimnee-vyrashchivanie"}, {"s": "mokritsy-v-teplitse-kak-izbavitsya-otzyvy", "t": "Мокрицы в теплице: как избавиться навсегда, отзывы и методы борьбы", "i": "🐛", "c": "vrediteli-i-zashchita"}, {"s": "mozhno-li-listvu-ispolzovat-kak-udobrenie-v-teplitsu", "t": "Осень в теплице: можно ли использовать листву как удобрение?", "i": "🟫", "c": "pochva-i-gryadki"}, {"s": "mozhno-li-polivat-pomidory-drozhzhami-vo-vremya-tsveteniya-i-plodonosheniya-v-teplitse-i-kak", "t": "Полив томатов дрожжами: можно ли в теплице при цветении и как делать", "i": "🌿", "c": "posadka-i-udobreniya"}, {"s": "mozhno-li-zakapyvat-yabloki-v-teplitsu-kak-udobrenie", "t": "Яблоки в теплицу: мифы, риски и правильная схема удобрения", "i": "🟫", "c": "pochva-i-gryadki"}, {"s": "mokh-na-fundamente-v-teplitse-chto-delat", "t": "Мох на фундаменте теплицы: причины, опасность и способы удаления", "i": "🧪", "c": "obrabotka-i-dezinfektsiya"}, {"s": "monofosfat-dlya-tomatov-v-teplitse-kak-primenyat", "t": "Монофосфат для томатов в теплице: схема подкормки и применение", "i": "🌿", "c": "posadka-i-udobreniya"}, {"s": "monokalij-fosfat-kak-primenyat-dlya-rassady-tomatov-i-pertsa-v-teplitse-iz-polikarbonata", "t": "Монокалий фосфат для томатов и перца: применение в теплице", "i": "🌿", "c": "posadka-i-udobreniya"}, {"s": "morshchatsya-listya-u-ogurtsov-v-teplitse-i-kak-s-etim-borotsya", "t": "Почему морщатся листья у огурцов в теплице: причины и лечение", "i": "🥒", "c": "bolezni-ogurtsov"}, {"s": "morshchinistost-listev-ogurtsov-v-teplitse-chto-delat", "t": "Морщинистые листья огурцов в теплице: причины, лечение и профилактика", "i": "🥒", "c": "bolezni-ogurtsov"}, {"s": "moshki-na-ogurtsakh-v-teplitse-kak-borotsya-narodnye-sredstva", "t": "Как бороться с мошками на огурцах в теплице: народные средства и методы", "i": "🐛", "c": "vrediteli-i-zashchita"}, {"s": "mozhno-li-podkarmlivat-pomidory-kurinym-pometom-vo-vremya-plodonosheniya-v-teplitse-i-kak", "t": "Подкормка помидоров куриным пометом в теплице: можно ли при плодоношении", "i": "🌿", "c": "posadka-i-udobreniya"}, {"s": "mozaika-na-pomidorakh-v-teplitse-kak-borotsya", "t": "Мозаика на томатах в теплице: симптомы, лечение и меры защиты", "i": "🍅", "c": "bolezni-tomatov"}, {"s": "moshkara-na-pomidorakh-chem-obrabotat-v-teplitse", "t": "Как избавиться от мошкары на помидорах в теплице: лучшие методы борьбы", "i": "🐛", "c": "vrediteli-i-zashchita"}, {"s": "mochevina-dlya-ogurtsov-v-teplitse-kogda-primenyat", "t": "Мочевина для огурцов в теплице: сроки, нормы и правила внесения", "i": "🌿", "c": "posadka-i-udobreniya"}, {"s": "mozaika-na-tomatakh-v-teplitse-chto-delat", "t": "Мозаика на томатах в теплице: что делать, признаки и лечение", "i": "🍅", "c": "bolezni-tomatov"}, {"s": "mokritsa-kak-izbavitsya-v-teplitse", "t": "Мокрица в теплице: как избавиться навсегда (методы 2026)", "i": "🐛", "c": "vrediteli-i-zashchita"}, {"s": "monofosfat-kaliya-chem-zamenit-dlya-tomatov-v-teplitse", "t": "Чем заменить монофосфат калия для томатов в теплице", "i": "🌿", "c": "posadka-i-udobreniya"}, {"s": "mozhno-li-opilki-dobavlyat-v-pochvu-kak-udobrenie-v-teplitse", "t": "Опилки в теплице: польза, вред и правила грамотного внесения", "i": "🟫", "c": "pochva-i-gryadki"}, {"s": "monokalijfosfat-dlya-tomatov-v-teplitse-opryskivanie-kak-razvesti", "t": "Монокалийфосфат для томатов: как развести и опрыскать в теплице", "i": "🌿", "c": "posadka-i-udobreniya"}, {"s": "monofosfat-kaliya-dlya-ogurtsov-v-teplitse-kak-prigotovit", "t": "Монофосфат калия для огурцов: как приготовить раствор", "i": "🌿", "c": "posadka-i-udobreniya"}, {"s": "moshka-na-ogurtsakh-v-teplitse-kak-borotsya", "t": "Как бороться с мошкой на огурцах в теплице: лучшие методы", "i": "🐛", "c": "vrediteli-i-zashchita"}, {"s": "moshka-na-ogurtsakh-v-teplitse-kak", "t": "Как бороться с мошкой на огурцах в теплице: эффективные методы", "i": "🐛", "c": "vrediteli-i-zashchita"}, {"s": "mozaika-tomatov-v-teplitse-chto-delat", "t": "Мозаика томатов в теплице: симптомы, лечение и меры профилактики", "i": "🍅", "c": "bolezni-tomatov"}, {"s": "mol-na-pomidorakh-v-teplitse-kak", "t": "Моль на помидорах в теплице: как бороться эффективно", "i": "🐛", "c": "vrediteli-i-zashchita"}, {"s": "mokritsy-kak-vyvesti-iz-teplitsy", "t": "Как вывести мокриц из теплицы: 7 проверенных методов борьбы", "i": "🐛", "c": "vrediteli-i-zashchita"}, {"s": "mokh-v-teplitse-posle-zimy-chto-delat", "t": "Мох в теплице после зимы: причины, опасные последствия и методы удаления", "i": "🧪", "c": "obrabotka-i-dezinfektsiya"}, {"s": "mozhno-li-strich-listya-u-ogurtsov-v-teplitse-i-kak", "t": "Стрижка листьев у огурцов в теплице: польза, вред и правильная схема", "i": "✂️", "c": "formirovanie-kustov"}, {"s": "monofosfat-kaliya-dlya-pomidorov-v-teplitse-kak-primenyat", "t": "Монофосфат калия для помидоров: инструкция по применению в теплице", "i": "🌿", "c": "posadka-i-udobreniya"}, {"s": "mokritsy-v-teplitse-edyat-rassadu-chto-delat", "t": "Мокрицы в теплице едят рассаду: эффективные методы борьбы и профилактики", "i": "🐛", "c": "vrediteli-i-zashchita"}, {"s": "monokalij-fosfat-kak-primenyat-dlya-pomidor-i-ogurtsov-v-teplitse", "t": "Монокалий фосфат для томатов и огурцов: инструкция", "i": "🌿", "c": "posadka-i-udobreniya"}, {"s": "mozhno-li-otryvat-nizhnie-listya-u-ogurtsov-v-teplitse-i-kak", "t": "Обрывание листьев у огурцов в теплице: правила и схема", "i": "✂️", "c": "formirovanie-kustov"}, {"s": "moshka-v-teplitse-na-pomidorakh-kak-borotsya", "t": "Как бороться с мошкой в теплице на помидорах: эффективные методы", "i": "🐛", "c": "vrediteli-i-zashchita"}, {"s": "mozaika-na-listyakh-ogurtsov-v-teplitse-chto", "t": "Мозаика на листьях огурцов в теплице: причины, лечение и профилактика", "i": "🥒", "c": "bolezni-ogurtsov"}, {"s": "mokh-v-teplitse-iz-polikarbonata-chto-delat", "t": "Мох в теплице из поликарбоната: причины и способы удаления", "i": "🔨", "c": "postrojka-i-konstruktsiya"}, {"s": "mozhno-li-polzovatsya-sernoj-shashkoj-v-teplitse-iz-polikarbonata-kogda-tam-rastet-zelen", "t": "Серная шашка в теплице с зеленью: можно ли использовать?", "i": "🧪", "c": "obrabotka-i-dezinfektsiya"}, {"s": "monofosfat-kaliya-dlya-pomidor-v-teplitse-kak-primenyat-otzyvy", "t": "Монофосфат калия для томатов в теплице: применение, дозировки и отзывы", "i": "🌿", "c": "posadka-i-udobreniya"}, {"s": "mochevina-dlya-pomidor-v-teplitse-kogda", "t": "Мочевина для томатов в теплице: сроки, дозировки и схема внесения", "i": "🌿", "c": "posadka-i-udobreniya"}, {"s": "moshkara-v-teplitse-kak-izbavitsya", "t": "Как избавиться от мошкары в теплице: народные и химические методы", "i": "🐛", "c": "vrediteli-i-zashchita"}, {"s": "monolitnyj-polikarbonat-kakaya-tolshchina-dlya-teplitsy", "t": "Какая толщина монолитного поликарбоната нужна для теплицы: выбор и монтаж", "i": "🔨", "c": "postrojka-i-konstruktsiya"}, {"s": "mol-na-pomidorakh-chem-obrabotat-v-teplitse", "t": "Моль на помидорах в теплице: как спасти урожай и чем обработать", "i": "🐛", "c": "vrediteli-i-zashchita"}, {"s": "moshki-v-teplitse-s-pomidorami-chem-obrabotat", "t": "Мошки в теплице с помидорами: чем обработать и как избавиться навсегда", "i": "🐛", "c": "vrediteli-i-zashchita"}, {"s": "mochevina-dlya-pomidor-v-teplitse-kak-razvodit", "t": "Мочевина для помидор в теплице: как разводить и подкармливать", "i": "🌿", "c": "posadka-i-udobreniya"}, {"s": "mokritsa-v-teplitse-kak-izbavitsya-narodnymi-sredstvami", "t": "Борьба с мокрицей в теплице: эффективные народные методы", "i": "🐛", "c": "vrediteli-i-zashchita"}, {"s": "mol-v-teplitse-chto-delat", "t": "Моль в теплице: что делать и как быстро избавиться от вредителя", "i": "🐛", "c": "vrediteli-i-zashchita"}, {"s": "monokalij-fosfat-kak-primenyat-dlya-ogurtsov-v-teplitse-iz-polikarbonata", "t": "Монокалий фосфат для огурцов в теплице: схема подкормок и дозировки", "i": "🌿", "c": "posadka-i-udobreniya"}, {"s": "mozhno-li-podstrigat-listya-u-ogurtsov-v-teplitse-i-kak", "t": "Можно ли обрывать листья у огурцов в теплице: правила и сроки", "i": "✂️", "c": "formirovanie-kustov"}, {"s": "mol-na-pomidorakh-v-teplitse-kak-borotsya", "t": "Моль на помидорах в теплице: как бороться эффективно", "i": "🐛", "c": "vrediteli-i-zashchita"}, {"s": "monofosfat-kaliya-dlya-tomatov-v-teplitse-dlya-chego", "t": "Монофосфат калия для томатов в теплице: зачем, дозировка и результат", "i": "🌿", "c": "posadka-i-udobreniya"}, {"s": "momordika-kak-vyrastit-v-teplitse", "t": "Выращивание момордики в теплице: пошаговая инструкция", "i": "🍄", "c": "ekzotika-i-griby"}, {"s": "mozhno-li-vyrashchivat-tomaty-i-ogurtsy-v-odnoj-teplitse-i-pochemu", "t": "Томаты и огурцы в одной теплице: совместимость, риски и правила", "i": "🔨", "c": "postrojka-i-konstruktsiya"}, {"s": "moshka-na-ogurtsakh-v-teplitse-kak-borotsya-chernaya", "t": "Черная мошка на огурцах в теплице: как бороться и спасти урожай", "i": "🐛", "c": "vrediteli-i-zashchita"}, {"s": "mozhno-li-obrabatyvat-ogurtsy-bornoj-kislotoj-vo-vremya-plodonosheniya-v-teplitse-i-kak", "t": "Обработка огурцов борной кислотой во время плодоношения: правила и дозы", "i": "🌿", "c": "posadka-i-udobreniya"}, {"s": "moshki-v-teplitse-chem-obrabotat", "t": "Мошки в теплице: чем обработать растения и почву", "i": "🐛", "c": "vrediteli-i-zashchita"}, {"s": "mozaika-na-listyakh-ogurtsov-v-teplitse-chem-lechit", "t": "Мозаика на листьях огурцов в теплице: причины, лечение и профилактика", "i": "🥒", "c": "bolezni-ogurtsov"}, {"s": "monofosfat-kaliya-dlya-tomatov-kak-ispolzovat-v-teplitse", "t": "Монофосфат калия для томатов в теплице: инструкция", "i": "🌿", "c": "posadka-i-udobreniya"}, {"s": "monofosfat-kaliya-dlya-vnekornevoj-podkormki-tomatov-v-teplitse-kak-primenyat", "t": "Монофосфат калия для томатов: как применять внекорневую подкормку", "i": "🌿", "c": "posadka-i-udobreniya"}, {"s": "moshki-v-teplitse-s-ogurtsami-kak-izbavitsya", "t": "Как избавиться от мошек в теплице с огурцами: эффективные методы борьбы", "i": "🐛", "c": "vrediteli-i-zashchita"}, {"s": "mozhno-li-obrezat-listya-u-kabachkov-v-teplitse-i-kakie", "t": "Обрезка листьев у кабачков в теплице: когда, как и какие удалять", "i": "✂️", "c": "formirovanie-kustov"}, {"s": "mozhno-li-seyat-redis-pod-zimu-i-kogda-v-teplitse", "t": "Посев редиса под зиму в теплице: сроки, технологии и выбор сортов", "i": "🌿", "c": "posadka-i-udobreniya"}, {"s": "monofosfat-kaliya-dlya-pomidor-v-teplitse-kak-primenyat", "t": "Монофосфат калия для томатов в теплице: инструкция по применению", "i": "🌿", "c": "posadka-i-udobreniya"}, {"s": "mokh-kak-mulcha-v-teplitse", "t": "Мох как мульча в теплице: применение сфагнума для почвы", "i": "🟫", "c": "pochva-i-gryadki"}, {"s": "moloko-i-jod-dlya-ogurtsov-v-teplitse-dlya-chego", "t": "Молоко с йодом для огурцов в теплице: польза, рецепт и защита", "i": "🥒", "c": "bolezni-ogurtsov"}, {"s": "monofosfat-kaliya-dlya-ogurtsov-v-teplitse-kak-primenyat-otzyvy-forum", "t": "Монофосфат калия для огурцов: применение, дозировки, отзывы", "i": "🌿", "c": "posadka-i-udobreniya"}, {"s": "moskovskij-agrokholding-gde-teplitsy", "t": "Московский агрохолдинг: где расположены теплицы и что там выращивают", "i": "❄️", "c": "zimnee-vyrashchivanie"}, {"s": "mozaichnye-listya-u-tomatov-v-teplitse-chto-delat", "t": "Мозаичные листья у томатов: диагностика и методы лечения", "i": "🍅", "c": "bolezni-tomatov"}, {"s": "mokritsa-nasekomoe-v-teplitse-kak-izbavitsya-vesnoj", "t": "Мокрица в теплице: как избавиться от вредителя весной эффективно", "i": "🐛", "c": "vrediteli-i-zashchita"}, {"s": "mol-pomidornaya-v-teplitse-chem-obrabotat", "t": "Моль помидорная в теплице: чем обработать и как уничтожить", "i": "🐛", "c": "vrediteli-i-zashchita"}, {"s": "mozhno-li-krasit-teplitsu-kogda-v-nej-rastut-rasteniya", "t": "Можно ли красить теплицу с растениями: риски и безопасные методы", "i": "🧪", "c": "obrabotka-i-dezinfektsiya"}, {"s": "mozaika-na-pomidorakh-v-teplitse-kak", "t": "Мозаика на томатах в теплице: как спасти урожай и предотвратить болезнь", "i": "🍅", "c": "bolezni-tomatov"}, {"s": "moshki-na-tomatakh-v-teplitse-kak-izbavitsya-narodnymi-sredstvami", "t": "Мошки на томатах в теплице: как избавиться народными средствами", "i": "🐛", "c": "vrediteli-i-zashchita"}, {"s": "mochevina-dlya-ogurtsov-v-teplitse-kak", "t": "Мочевина для огурцов в теплице: как правильно подкормить", "i": "🌿", "c": "posadka-i-udobreniya"}, {"s": "monofosfat-kaliya-dlya-ogurtsov-v-teplitse-kak-primenyat-otzyvy", "t": "Монофосфат калия для огурцов в теплице: применение и отзывы", "i": "🌿", "c": "posadka-i-udobreniya"}, {"s": "mozaika-na-listyakh-ogurtsov-v-teplitse-chem-lechit-foto", "t": "Мозаика на огурцах в теплице: симптомы, лечение и профилактика", "i": "🥒", "c": "bolezni-ogurtsov"}, {"s": "monofosfat-kaliya-dlya-tomatov-v-teplitse-kak-primenyat-otzyvy-forum", "t": "Монофосфат калия для томатов в теплице: применение, дозировка и отзывы", "i": "🌿", "c": "posadka-i-udobreniya"}, {"s": "mokritsa-trava-v-teplitse-kak-izbavitsya", "t": "Мокрица в теплице: как избавиться от сорняка навсегда", "i": "🐛", "c": "vrediteli-i-zashchita"}, {"s": "mozhno-li-otryvat-listya-u-ogurtsov-v-teplitse-i-kak-s-etim-borotsya", "t": "Можно ли обрывать листья у огурцов: правила и последствия", "i": "✂️", "c": "formirovanie-kustov"}, {"s": "molochnaya-syvorotka-dlya-rastenij-kak-udobrenie-v-teplitse-dlya-ogurtsov", "t": "Молочная сыворотка для огурцов в теплице: рецепты подкормки", "i": "🌿", "c": "posadka-i-udobreniya"}, {"s": "monofosfat-kaliya-kak-primenyat-dlya-tomatov-v-teplitse", "t": "Монофосфат калия для томатов в теплице: схемы подкормки и нормы расхода", "i": "🌿", "c": "posadka-i-udobreniya"}, {"s": "mol-v-teplitse-kak-izbavitsya-narodnymi-sredstvami", "t": "Моль в теплице: как избавиться народными средствами быстро и безопасно", "i": "🐛", "c": "vrediteli-i-zashchita"}, {"s": "moshki-na-pomidorakh-v-teplitse-kak-borotsya", "t": "Мошки на помидорах в теплице: как бороться с белыми и черными вредителями", "i": "🐛", "c": "vrediteli-i-zashchita"}, {"s": "moshka-v-teplitse-kak-izbavitsya", "t": "Как избавиться от мошки в теплице: народные и химические методы", "i": "🐛", "c": "vrediteli-i-zashchita"}, {"s": "mozaika-u-ogurtsov-v-teplitse-chto-delat", "t": "Мозаика у огурцов в теплице: что делать и как спасти урожай", "i": "🥒", "c": "bolezni-ogurtsov"}, {"s": "mozhno-li-sushit-luk-v-teplitse-gde-rastut-i-sozrevayut-pomidory", "t": "Сушка лука в теплице с помидорами: Можно ли и как сохранить урожай?", "i": "📅", "c": "sezonnye-raboty"}, {"s": "mokh-v-teplitse-posle-zimy-kak-izbavitsya", "t": "Как избавиться от мха в теплице после зимы: 7 проверенных методов", "i": "🧪", "c": "obrabotka-i-dezinfektsiya"}, {"s": "mozaika-na-listyakh-ogurtsov-v-teplitse-chto-delat-foto", "t": "Мозаика на листьях огурцов в теплице: причины, лечение и фото симптомов", "i": "🥒", "c": "bolezni-ogurtsov"}, {"s": "mozhno-li-svezheskoshennuyu-travu-ispolzovat-kak-mulchu-v-teplitse", "t": "Свежескошенная трава как мульча в теплице: польза и вред", "i": "🟫", "c": "pochva-i-gryadki"}, {"s": "moya-vysokourozhajnaya-teplitsa-kak-vyrastit-vysokie-urozhai-tomatov-pertsa-baklazhanov-i-ogurtsov-pod-odnoj-kryshej-galina-kizima", "t": "Моя высокоурожайная теплица: секреты Галины Кизимы для томатов, огурцов, перцев и баклажанов", "i": "🌿", "c": "posadka-i-udobreniya"}, {"s": "moshka-v-teplitse-na-ogurtsakh-kak-izbavitsya", "t": "Мошка в теплице на огурцах: как избавиться быстро", "i": "🐛", "c": "vrediteli-i-zashchita"}, {"s": "mozhno-li-sobirat-zelenye-pomidory-v-teplitse-i-chto-delat", "t": "Сбор зеленых помидоров в теплице: когда, как и что делать дальше", "i": "📅", "c": "sezonnye-raboty"}, {"s": "mozaichnost-listev-ogurtsov-v-teplitse-chto-delat", "t": "Мозаичность листьев огурцов в теплице: лечение и профилактика", "i": "🥒", "c": "bolezni-ogurtsov"}, {"s": "mozhno-li-sushit-luk-v-teplitse-gde-rastut-pomidory", "t": "Сушка лука в теплице с томатами: можно ли и как сделать безопасно", "i": "📅", "c": "sezonnye-raboty"}, {"s": "mokh-v-teplitse-iz-polikarbonata-kak", "t": "Как убрать мох в теплице из поликарбоната: эффективные методы борьбы", "i": "🧪", "c": "obrabotka-i-dezinfektsiya"}, {"s": "mokh-v-teplitse-iz-polikarbonata-kak-izbavitsya-posle-zimy", "t": "Как избавиться от мха в теплице из поликарбоната после зимы: пошаговая инструкция", "i": "🧪", "c": "obrabotka-i-dezinfektsiya"}, {"s": "moshki-na-ogurtsakh-v-teplitse-kak-borotsya", "t": "Борьба с мошками на огурцах в теплице: методы, профилактика и средства", "i": "🐛", "c": "vrediteli-i-zashchita"}]