[{"s": "zimnyaya-teplitsa-chem-otaplivat", "t": "Зимняя теплица: чем отапливать и как сэкономить", "i": "🔥", "c": "otoplenie-i-klimat"}, {"s": "zimnyaya-teplitsa-v-sibiri-kak-biznes-otzyvy", "t": "Зимняя теплица в Сибири как бизнес: отзывы, реальные цифры и риски", "i": "❄️", "c": "zimnee-vyrashchivanie"}, {"s": "zimnie-teplitsy-kak-sdelat", "t": "Как сделать зимнюю теплицу: пошаговое руководство и схемы", "i": "❄️", "c": "zimnee-vyrashchivanie"}, {"s": "zimnyaya-teplitsa-kak-postroit", "t": "Как построить зимнюю теплицу: пошаговая инструкция", "i": "🔨", "c": "postrojka-i-konstruktsiya"}, {"s": "zimnyaya-teplitsa-kak-sdelat-pravilno", "t": "Зимняя теплица своими руками: как сделать правильно и надежно", "i": "❄️", "c": "zimnee-vyrashchivanie"}, {"s": "zimnyaya-teplitsa-kak-biznes-rentabelnost", "t": "Зимняя теплица как бизнес: расчет рентабельности и прибыль", "i": "❄️", "c": "zimnee-vyrashchivanie"}, {"s": "zimnyaya-teplitsa-chto-vyrashchivat-zimoj", "t": "Что выращивать в зимней теплице: лучшие культуры и сорта для урожая круглый год", "i": "❄️", "c": "zimnee-vyrashchivanie"}, {"s": "zimoj-teplitsu-derzhat-otkrytoj-ili-zakrytoj-kak-pravilno", "t": "Теплица зимой: держать открытой или закрытой? Правильный режим", "i": "❄️", "c": "zimnee-vyrashchivanie"}, {"s": "zimnyaya-teplitsa-dlya-luka-kak-sdelat-video", "t": "Как сделать зимнюю теплицу для лука: видео-инструкция и план", "i": "❄️", "c": "zimnee-vyrashchivanie"}, {"s": "zimnyaya-teplitsa-s-chego-nachat", "t": "Зимняя теплица: с чего начать строительство и оборудование", "i": "❄️", "c": "zimnee-vyrashchivanie"}, {"s": "zimnie-teplitsy-kak-biznes", "t": "Зимние теплицы как бизнес: расчет окупаемости и тонкости", "i": "❄️", "c": "zimnee-vyrashchivanie"}, {"s": "zimnyaya-teplitsa-chto-vyrashchivat", "t": "Зимняя теплица: что выращивать в холода для урожая", "i": "❄️", "c": "zimnee-vyrashchivanie"}, {"s": "zimnie-teplitsy-kak-biznes-ideya", "t": "Зимние теплицы как бизнес: расчеты, плюсы, риски и пошаговый план", "i": "❄️", "c": "zimnee-vyrashchivanie"}, {"s": "zimnyaya-teplitsa-kak-pristrojka-k-domu", "t": "Зимняя теплица-пристройка к дому: проекты, отопление и выращивание", "i": "🔨", "c": "postrojka-i-konstruktsiya"}, {"s": "zimnyaya-teplitsa-kak-biznes-otzyvy", "t": "Зимняя теплица как бизнес: отзывы, рентабельность и риски", "i": "❄️", "c": "zimnee-vyrashchivanie"}, {"s": "zimnyaya-teplitsa-v-sibiri-kak-biznes-otzyvy-vladeltsev", "t": "Зимняя теплица в Сибири бизнес: отзывы владельцев, доходы и риски", "i": "❄️", "c": "zimnee-vyrashchivanie"}, {"s": "zimnyaya-teplitsa-kak-sdelat", "t": "Зимняя теплица своими руками: пошаговая инструкция и выбор отопления", "i": "🔨", "c": "postrojka-i-konstruktsiya"}, {"s": "zimnyaya-teplitsa-chto-posadit", "t": "Что посадить в зимней теплице: лучшие культуры и сроки", "i": "❄️", "c": "zimnee-vyrashchivanie"}, {"s": "zimnyaya-teplitsa-kak-biznes", "t": "Зимняя теплица как бизнес: рентабельность и технологии", "i": "❄️", "c": "zimnee-vyrashchivanie"}]